hyperimpute/__init__.py
hyperimpute/logger.py
hyperimpute/version.py
hyperimpute/exceptions/__init__.py
hyperimpute/hooks/__init__.py
hyperimpute/plugins/__init__.py
hyperimpute/plugins/core/__init__.py
hyperimpute/plugins/core/base_plugin.py
hyperimpute/plugins/core/device.py
hyperimpute/plugins/core/params.py
hyperimpute/plugins/imputers/__init__.py
hyperimpute/plugins/imputers/_hyperimpute_internals.py
hyperimpute/plugins/imputers/base.py
hyperimpute/plugins/imputers/plugin_EM.py
hyperimpute/plugins/imputers/plugin_gain.py
hyperimpute/plugins/imputers/plugin_hyperimpute.py
hyperimpute/plugins/imputers/plugin_ice.py
hyperimpute/plugins/imputers/plugin_mean.py
hyperimpute/plugins/imputers/plugin_median.py
hyperimpute/plugins/imputers/plugin_mice.py
hyperimpute/plugins/imputers/plugin_miracle.py
hyperimpute/plugins/imputers/plugin_missforest.py
hyperimpute/plugins/imputers/plugin_miwae.py
hyperimpute/plugins/imputers/plugin_most_frequent.py
hyperimpute/plugins/imputers/plugin_nop.py
hyperimpute/plugins/imputers/plugin_sinkhorn.py
hyperimpute/plugins/imputers/plugin_sklearn_ice.py
hyperimpute/plugins/imputers/plugin_sklearn_missforest.py
hyperimpute/plugins/imputers/plugin_softimpute.py
hyperimpute/plugins/prediction/__init__.py
hyperimpute/plugins/prediction/base.py
hyperimpute/plugins/prediction/classifiers/__init__.py
hyperimpute/plugins/prediction/classifiers/base.py
hyperimpute/plugins/prediction/classifiers/plugin_catboost.py
hyperimpute/plugins/prediction/classifiers/plugin_kneighbors.py
hyperimpute/plugins/prediction/classifiers/plugin_logistic_regression.py
hyperimpute/plugins/prediction/classifiers/plugin_neural_nets.py
hyperimpute/plugins/prediction/classifiers/plugin_random_forest.py
hyperimpute/plugins/prediction/classifiers/plugin_svc.py
hyperimpute/plugins/prediction/classifiers/plugin_xgboost.py
hyperimpute/plugins/prediction/regression/__init__.py
hyperimpute/plugins/prediction/regression/base.py
hyperimpute-0.1.17.dist-info/LICENSE
hyperimpute-0.1.17.dist-info/METADATA
hyperimpute-0.1.17.dist-info/WHEEL
hyperimpute-0.1.17.dist-info/top_level.txt
hyperimpute-0.1.17.dist-info/RECORD
