Metadata-Version: 2.1
Name: hyperimpute
Version: 0.1.17
Summary: A library for NaNs and nulls
Home-page: https://www.vanderschaar-lab.com/
Author: Bogdan Cebere
Author-email: bcc38@cam.ac.uk
License: MIT
Platform: any
Classifier: Programming Language :: Python :: 3
Classifier: Topic :: Scientific/Engineering :: Artificial Intelligence
Classifier: Intended Audience :: Healthcare Industry
Classifier: License :: OSI Approved :: MIT License
Classifier: Operating System :: OS Independent
License-File: LICENSE
Requires-Dist: scikit-learn (>=1.0)
Requires-Dist: pandas (>=1.3)
Requires-Dist: torch (>=1.10.0)
Requires-Dist: numpy (>=1.20)
Requires-Dist: catboost (>=1.0.5)
Requires-Dist: optuna (>=3.1)
Requires-Dist: loguru (==0.6.0)
Requires-Dist: xgboost (>=1.6.1)
Requires-Dist: miracle-imputation (>=0.1.3)
Requires-Dist: lightgbm
Requires-Dist: redis
Requires-Dist: cloudpickle
Requires-Dist: geomloss
Requires-Dist: pydantic
Requires-Dist: jupyter
Requires-Dist: notebook
Requires-Dist: importlib-metadata ; python_version < "3.8"
Provides-Extra: testing
Requires-Dist: setuptools ; extra == 'testing'
Requires-Dist: pytest ; extra == 'testing'
Requires-Dist: pytest-cov ; extra == 'testing'
Requires-Dist: pytest-benchmark ; extra == 'testing'
Requires-Dist: tabulate ; extra == 'testing'
Requires-Dist: bandit ; extra == 'testing'
Requires-Dist: black ; extra == 'testing'
Requires-Dist: flake8 ; extra == 'testing'
Requires-Dist: pre-commit ; extra == 'testing'
Requires-Dist: xlrd ; extra == 'testing'
